{
  "gitSyncId": "67dd1afa8f16fa2ec6c6d057_af89ef75-6d55-422d-b18f-d8258524907a",
  "id": "QUERY_Query_low_stock",
  "pluginId": "mongo-plugin",
  "pluginType": "DB",
  "unpublishedAction": {
    "actionConfiguration": {
      "encodeParamsToggle": true,
      "formData": {
        "aggregate": {
          "arrayPipelines": {
            "data": ""
          },
          "limit": {
            "data": "10"
          }
        },
        "body": {
          "data": "{\n  \"find\": \"MEDICATION\",\n  \"filter\": {\n    \"stock_quantity\": { \"$lt\": 50 }\n  },\n  \"projection\": {\n    \"_id\": 0,\n    \"med_id\": 1,\n    \"med_name\": 1,\n    \"stock_quantity\": 1,\n    \"unit_price\": 1,\n    \"description\": 1\n  }\n}"
        },
        "collection": {
          "data": "MEDICATION"
        },
        "command": {
          "data": "RAW"
        },
        "count": {
          "query": {
            "data": ""
          }
        },
        "delete": {
          "limit": {
            "data": "SINGLE"
          },
          "query": {
            "data": ""
          }
        },
        "distinct": {
          "key": {
            "data": ""
          },
          "query": {
            "data": ""
          }
        },
        "find": {
          "limit": {
            "data": ""
          },
          "projection": {
            "data": ""
          },
          "query": {
            "data": "{ stock_quantity: { $lt: 50 } }"
          },
          "skip": {
            "data": ""
          },
          "sort": {
            "data": ""
          }
        },
        "insert": {
          "documents": {
            "data": ""
          }
        },
        "smartSubstitution": {
          "data": true
        },
        "updateMany": {
          "limit": {
            "data": "SINGLE"
          },
          "query": {
            "data": ""
          },
          "update": {
            "data": ""
          }
        }
      },
      "paginationType": "NONE",
      "timeoutInMillisecond": 10000
    },
    "confirmBeforeExecute": false,
    "datasource": {
      "id": "G3_DBMongoDB",
      "isAutoGenerated": false,
      "name": "G3_DBMongoDB",
      "pluginId": "mongo-plugin"
    },
    "dynamicBindingPathList": [],
    "executeOnLoad": false,
    "name": "Query_low_stock",
    "pageId": "QUERY",
    "userSetOnLoad": false
  }
}